LICENSE
MANIFEST.in
README.rst
setup.py
django_ratings.egg-info/PKG-INFO
django_ratings.egg-info/SOURCES.txt
django_ratings.egg-info/dependency_links.txt
django_ratings.egg-info/top_level.txt
djangoratings/__init__.py
djangoratings/admin.py
djangoratings/default_settings.py
djangoratings/exceptions.py
djangoratings/fields.py
djangoratings/forms.py
djangoratings/managers.py
djangoratings/models.py
djangoratings/tests.py
djangoratings/views.py
djangoratings/management/__init__.py
djangoratings/management/commands/__init__.py
djangoratings/management/commands/update_recommendations.py
djangoratings/migrations/0001_initial.py
djangoratings/migrations/0002_add_mean_and_stddev.py
djangoratings/migrations/0003_add_correlations.py
djangoratings/migrations/0004_rethink_recommendations.py
djangoratings/migrations/0005_add_exclusions.py
djangoratings/migrations/0006_add_cookies.py
djangoratings/migrations/__init__.py
djangoratings/templatetags/__init__.py
djangoratings/templatetags/ratings.py