Metadata-Version: 1.0
Name: django-ratings
Version: 0.3.6
Summary: Generic Ratings in Django
Home-page: http://github.com/dcramer/django-ratings
Author: David Cramer
Author-email: dcramer@gmail.com
License: UNKNOWN
Platform: UNKNOWN
Classifier: Framework :: Django
Classifier: Intended Audience :: Developers
Classifier: Intended Audience :: System Administrators
Classifier: Operating System :: OS Independent
Classifier: Topic :: Software Development
